dolce/__init__.py
dolce/cfg.py
dolce/err.py
dolce/reader.py
dolce/realtime.py
dolce/utils.py
dolce/version.py
dolce/writer.py
dolce-151024.dist-info/LICENSE
dolce-151024.dist-info/METADATA
dolce-151024.dist-info/WHEEL
dolce-151024.dist-info/top_level.txt
dolce-151024.dist-info/RECORD
