Metadata-Version: 2.1
Name: dolce
Version: 151024
Summary: Algorithmic composition utilities
Author-email: Amir Teymuri <amtework@gmail.com>
License: GNU GENERAL PUBLIC LICENSE
Project-URL: Homepage, https://codeberg.org/dolce/src.git
Classifier: Programming Language :: Python :: 3
Classifier: License :: OSI Approved :: GNU Affero General Public License v3
Classifier: Operating System :: OS Independent
Requires-Python: >=3.5
License-File: LICENSE
Requires-Dist: python-rtmidi
Requires-Dist: MIDIUtil
Requires-Dist: mido
Requires-Dist: numpy
